<manifest alg="2" build="2017.0.1.363" opt="true" iceEnabled="true" iceMarkupVersion="2" iceEnabledOptions="link,responsive,cachebuster" exportTarget="other" domain="http;//carltongroup.com" resolutions="1x" timestamp="1485464895849">
  <folder name="css">
    <file name="site_global.css" crc="4111456539"/>
    <file name="index.css" crc="154492950" ref="index"/>
    <file name="nomq_index.css" crc="3906468352" ref="index"/>
  </folder>
  <folder name="scripts">
    <file name="jquery-1.8.3.min.js" crc="209076791" ref="index"/>
    <file name="museutils.js" crc="4148063285" ref="index"/>
    <file name="whatinput.js" crc="86476730" ref="index"/>
    <file name="museconfig.js" crc="4179431180" ref="index"/>
    <file name="jquery.watch.js" crc="437028206" ref="index"/>
    <file name="require.js" crc="4159430777" ref="index"/>
    <file name="jquery.museresponsive.js" crc="3991890305" ref="index"/>
  </folder>
  <folder name="images">
    <file name="u167-4.png" crc="4193795333" ref="index"/>
    <file name="mkljk_main01_r.jpg" crc="154796597" seo="true" ref="index"/>
    <file name="u171-7.png" crc="4001147647" ref="index"/>
    <file name="blank.gif" crc="4208392903" ref="index"/>
    <file name="1-2-crop-u222.jpg" crc="3999628682" ref="index"/>
    <file name="u219-7.png" crc="3950217549" ref="index"/>
    <file name="03cf9abd-9c5e-4115-a1e6-6f7ab319d80.jpg" crc="487176314" seo="true" ref="index"/>
    <file name="u264-7.png" crc="3761899036" ref="index"/>
    <file name="facebook.svg" crc="4256033763" seo="true" ref="index"/>
    <file name="facebook_poster_.png" crc="253634134" ref="index"/>
    <file name="twitter.svg" crc="469322800" seo="true" ref="index"/>
    <file name="twitter_poster_.png" crc="503451678" ref="index"/>
    <file name="linkedin.svg" crc="3827854651" seo="true" ref="index"/>
    <file name="linkedin_poster_.png" crc="191103562" ref="index"/>
    <file name="u268_states.png" crc="190262050" ref="index"/>
    <file name="u268_states-r.png" crc="190262050" ref="index"/>
    <file name="u167-42.png" crc="383130766" ref="index"/>
    <file name="u171-72.png" crc="3900010298" ref="index"/>
    <file name="u219-72.png" crc="167955542" ref="index"/>
    <file name="1-2-crop-u2222.jpg" crc="203109567" ref="index"/>
    <file name="u264-72.png" crc="515854101" ref="index"/>
    <file name="u268_states2.png" crc="4118977690" ref="index"/>
    <file name="u268_states-r2.png" crc="4118977690" ref="index"/>
    <file name="u1813_states.png" crc="190262050" ref="index"/>
    <file name="u1813_states-r.png" crc="190262050" ref="index"/>
    <file name="u1835_states.png" crc="190262050" ref="index"/>
    <file name="u1835_states-r.png" crc="190262050" ref="index"/>
    <file name="u1813_states2.png" crc="4118977690" ref="index"/>
    <file name="u1813_states-r2.png" crc="4118977690" ref="index"/>
    <file name="u1835_states2.png" crc="4118977690" ref="index"/>
    <file name="u1835_states-r2.png" crc="4118977690" ref="index"/>
    <file name="mkljk_main01_r339x227.jpg" crc="3944808810" seo="true" ref="index"/>
    <file name="u167-43.png" crc="4187487685" ref="index"/>
    <file name="u171-73.png" crc="191817155" ref="index"/>
    <file name="u219-73.png" crc="245577302" ref="index"/>
    <file name="1-2-crop-u2223.jpg" crc="66725943" ref="index"/>
    <file name="03cf9abd-9c5e-4115-a1e6-6f7ab319d80339x196.jpg" crc="4115210177" seo="true" ref="index"/>
    <file name="u264-73.png" crc="4261413649" ref="index"/>
    <file name="u268_states3.png" crc="140648039" ref="index"/>
    <file name="u268_states-r3.png" crc="140648039" ref="index"/>
    <file name="u1813_states3.png" crc="140648039" ref="index"/>
    <file name="u1813_states-r3.png" crc="140648039" ref="index"/>
    <file name="u1835_states3.png" crc="140648039" ref="index"/>
    <file name="u1835_states-r3.png" crc="140648039" ref="index"/>
    <file name="mkljk_main01_r284x190.jpg" crc="490493269" seo="true" ref="index"/>
    <file name="u167-44.png" crc="494539251" ref="index"/>
    <file name="u171-74.png" crc="165343705" ref="index"/>
    <file name="u219-74.png" crc="25483616" ref="index"/>
    <file name="1-2-crop-u2224.jpg" crc="36182443" ref="index"/>
    <file name="03cf9abd-9c5e-4115-a1e6-6f7ab319d80284x164.jpg" crc="443362474" seo="true" ref="index"/>
    <file name="u264-74.png" crc="3997744994" ref="index"/>
    <file name="u268_states4.png" crc="4269315014" ref="index"/>
    <file name="u268_states-r4.png" crc="4269315014" ref="index"/>
    <file name="u1813_states4.png" crc="4269315014" ref="index"/>
    <file name="u1813_states-r4.png" crc="4269315014" ref="index"/>
    <file name="u1835_states4.png" crc="4269315014" ref="index"/>
    <file name="u1835_states-r4.png" crc="4269315014" ref="index"/>
    <file name="mkljk_main01_r454x304.jpg" crc="506371463" seo="true" ref="index"/>
    <file name="03cf9abd-9c5e-4115-a1e6-6f7ab319d80454x262.jpg" crc="145422569" seo="true" ref="index"/>
    <file name="u167-45.png" crc="3896863799" ref="index"/>
    <file name="u171-75.png" crc="30903572" ref="index"/>
    <file name="u219-75.png" crc="182819959" ref="index"/>
    <file name="1-2-crop-u2225.jpg" crc="147634376" ref="index"/>
    <file name="u264-75.png" crc="226646164" ref="index"/>
    <file name="u268_states5.png" crc="35723177" ref="index"/>
    <file name="u268_states-r5.png" crc="35723177" ref="index"/>
    <file name="u1813_states5.png" crc="35723177" ref="index"/>
    <file name="u1813_states-r5.png" crc="35723177" ref="index"/>
    <file name="u1835_states5.png" crc="35723177" ref="index"/>
    <file name="u1835_states-r5.png" crc="35723177" ref="index"/>
  </folder>
  <file name="index.html" crc="292499609" seo="true" mt="1485464878886" redirect="true"/>
</manifest>